LICENSE.txt
MANIFEST.in
README.txt
RELEASE-VERSION
continuum.py
ez_setup.py
setup.cfg
setup.py
version.py
python_continuum.egg-info/PKG-INFO
python_continuum.egg-info/SOURCES.txt
python_continuum.egg-info/dependency_links.txt
python_continuum.egg-info/top_level.txt
tests/__init__.py
tests/test_continuum.py