Metadata-Version: 1.0
Name: python-continuum
Version: 0.1.0
Summary: Consistent hashing for Python
Home-page: http://www.joachim-bauch.de/projects/python-continuum/
Author: Joachim Bauch
Author-email: mail@joachim-bauch.de
License: LGPL
Download-URL: http://pypi.python.org/pypi/python-continuum/
Keywords: consistent hashing
Platform: UNKNOWN
Classifier: Development Status :: 5 - Production/Stable
Classifier: Programming Language :: Python
Classifier: Topic :: Software Development :: Libraries :: Python Modules
Classifier: Intended Audience :: Developers
Classifier: License :: OSI Approved :: GNU Library or Lesser General Public License (LGPL)
Classifier: Operating System :: OS Independent
